LICENSE
README.md
verval/__init__.py
verval/__main__.py
verval/version.py
verval-0.1.0.dist-info/LICENSE
verval-0.1.0.dist-info/WHEEL
verval-0.1.0.dist-info/METADATA
verval-0.1.0.dist-info/RECORD
