Metadata-Version: 2.1
Name: verval
Version: 0.1.0
Summary: Client python verval* sdm.data.kemdikbud
Home-page: https://github.com/dapodix/verval
License: GPL-3
Author: hexatester
Author-email: habibrohman@gmail.com
Requires-Python: >=3.7,<4.0
Classifier: License :: Other/Proprietary License
Classifier: Programming Language :: Python :: 3
Classifier: Programming Language :: Python :: 3.7
Classifier: Programming Language :: Python :: 3.8
Classifier: Programming Language :: Python :: 3.9
Requires-Dist: bs4 (>=0.0.1,<0.0.2)
Requires-Dist: dacite (>=1.6.0,<2.0.0)
Requires-Dist: requests (>=2.25.1,<3.0.0)
Project-URL: Repository, https://github.com/dapodix/verval
